{
  "run_id": "math500",
  "started_at": "2025-12-30T13:55:00Z",
  "updated_at": "2025-12-30T14:04:07Z",
  "total": 50,
  "completed": 0,
  "current": {
    "sample_index": 17,
    "sample_id": "test/algebra/1082.json",
    "dataset_index": 183,
    "phase": "pass@1",
    "sc_done": 0,
    "sc_total": 256
  },
  "aggregate": {
    "n": 0,
    "pass@1": null,
    "pass@k": {
      "pass@8": null,
      "pass@9": null,
      "pass@10": null,
      "pass@11": null,
      "pass@12": null,
      "pass@13": null,
      "pass@14": null,
      "pass@15": null,
      "pass@16": null,
      "pass@17": null,
      "pass@18": null,
      "pass@19": null,
      "pass@20": null,
      "pass@21": null,
      "pass@22": null,
      "pass@23": null,
      "pass@24": null,
      "pass@25": null,
      "pass@26": null,
      "pass@27": null,
      "pass@28": null,
      "pass@29": null,
      "pass@30": null,
      "pass@31": null,
      "pass@32": null,
      "pass@33": null,
      "pass@34": null,
      "pass@35": null,
      "pass@36": null,
      "pass@37": null,
      "pass@38": null,
      "pass@39": null,
      "pass@40": null,
      "pass@41": null,
      "pass@42": null,
      "pass@43": null,
      "pass@44": null,
      "pass@45": null,
      "pass@46": null,
      "pass@47": null,
      "pass@48": null,
      "pass@49": null,
      "pass@50": null,
      "pass@51": null,
      "pass@52": null,
      "pass@53": null,
      "pass@54": null,
      "pass@55": null,
      "pass@56": null,
      "pass@57": null,
      "pass@58": null,
      "pass@59": null,
      "pass@60": null,
      "pass@61": null,
      "pass@62": null,
      "pass@63": null,
      "pass@64": null,
      "pass@65": null,
      "pass@66": null,
      "pass@67": null,
      "pass@68": null,
      "pass@69": null,
      "pass@70": null,
      "pass@71": null,
      "pass@72": null,
      "pass@73": null,
      "pass@74": null,
      "pass@75": null,
      "pass@76": null,
      "pass@77": null,
      "pass@78": null,
      "pass@79": null,
      "pass@80": null,
      "pass@81": null,
      "pass@82": null,
      "pass@83": null,
      "pass@84": null,
      "pass@85": null,
      "pass@86": null,
      "pass@87": null,
      "pass@88": null,
      "pass@89": null,
      "pass@90": null,
      "pass@91": null,
      "pass@92": null,
      "pass@93": null,
      "pass@94": null,
      "pass@95": null,
      "pass@96": null,
      "pass@97": null,
      "pass@98": null,
      "pass@99": null,
      "pass@100": null,
      "pass@101": null,
      "pass@102": null,
      "pass@103": null,
      "pass@104": null,
      "pass@105": null,
      "pass@106": null,
      "pass@107": null,
      "pass@108": null,
      "pass@109": null,
      "pass@110": null,
      "pass@111": null,
      "pass@112": null,
      "pass@113": null,
      "pass@114": null,
      "pass@115": null,
      "pass@116": null,
      "pass@117": null,
      "pass@118": null,
      "pass@119": null,
      "pass@120": null,
      "pass@121": null,
      "pass@122": null,
      "pass@123": null,
      "pass@124": null,
      "pass@125": null,
      "pass@126": null,
      "pass@127": null,
      "pass@128": null,
      "pass@129": null,
      "pass@130": null,
      "pass@131": null,
      "pass@132": null,
      "pass@133": null,
      "pass@134": null,
      "pass@135": null,
      "pass@136": null,
      "pass@137": null,
      "pass@138": null,
      "pass@139": null,
      "pass@140": null,
      "pass@141": null,
      "pass@142": null,
      "pass@143": null,
      "pass@144": null,
      "pass@145": null,
      "pass@146": null,
      "pass@147": null,
      "pass@148": null,
      "pass@149": null,
      "pass@150": null,
      "pass@151": null,
      "pass@152": null,
      "pass@153": null,
      "pass@154": null,
      "pass@155": null,
      "pass@156": null,
      "pass@157": null,
      "pass@158": null,
      "pass@159": null,
      "pass@160": null,
      "pass@161": null,
      "pass@162": null,
      "pass@163": null,
      "pass@164": null,
      "pass@165": null,
      "pass@166": null,
      "pass@167": null,
      "pass@168": null,
      "pass@169": null,
      "pass@170": null,
      "pass@171": null,
      "pass@172": null,
      "pass@173": null,
      "pass@174": null,
      "pass@175": null,
      "pass@176": null,
      "pass@177": null,
      "pass@178": null,
      "pass@179": null,
      "pass@180": null,
      "pass@181": null,
      "pass@182": null,
      "pass@183": null,
      "pass@184": null,
      "pass@185": null,
      "pass@186": null,
      "pass@187": null,
      "pass@188": null,
      "pass@189": null,
      "pass@190": null,
      "pass@191": null,
      "pass@192": null,
      "pass@193": null,
      "pass@194": null,
      "pass@195": null,
      "pass@196": null,
      "pass@197": null,
      "pass@198": null,
      "pass@199": null,
      "pass@200": null,
      "pass@201": null,
      "pass@202": null,
      "pass@203": null,
      "pass@204": null,
      "pass@205": null,
      "pass@206": null,
      "pass@207": null,
      "pass@208": null,
      "pass@209": null,
      "pass@210": null,
      "pass@211": null,
      "pass@212": null,
      "pass@213": null,
      "pass@214": null,
      "pass@215": null,
      "pass@216": null,
      "pass@217": null,
      "pass@218": null,
      "pass@219": null,
      "pass@220": null,
      "pass@221": null,
      "pass@222": null,
      "pass@223": null,
      "pass@224": null,
      "pass@225": null,
      "pass@226": null,
      "pass@227": null,
      "pass@228": null,
      "pass@229": null,
      "pass@230": null,
      "pass@231": null,
      "pass@232": null,
      "pass@233": null,
      "pass@234": null,
      "pass@235": null,
      "pass@236": null,
      "pass@237": null,
      "pass@238": null,
      "pass@239": null,
      "pass@240": null,
      "pass@241": null,
      "pass@242": null,
      "pass@243": null,
      "pass@244": null,
      "pass@245": null,
      "pass@246": null,
      "pass@247": null,
      "pass@248": null,
      "pass@249": null,
      "pass@250": null,
      "pass@251": null,
      "pass@252": null,
      "pass@253": null,
      "pass@254": null,
      "pass@255": null,
      "pass@256": null
    }
  },
  "errors": 17
}